README.md
setup.py
django_project_info.egg-info/PKG-INFO
django_project_info.egg-info/SOURCES.txt
django_project_info.egg-info/dependency_links.txt
django_project_info.egg-info/not-zip-safe
django_project_info.egg-info/requires.txt
django_project_info.egg-info/top_level.txt
project_info/__init__.py
project_info/context_processors.py