Metadata-Version: 1.0
Name: django-project-info
Version: 1.0.2
Summary: A small plugin which takes a configuration (like Bower or npm) and it provides data via contextprocessors.
Home-page: https://github.com/druids/django-project-info
Author: Lukas Rychtecky
Author-email: lukas.rychtecky@gmail.com
License: MIT
Keywords: django,project-info
Platform: UNKNOWN
